[
  {
    "identifier": "C1",
    "reservationsList": [
      {
        "date": "03/25/24",
        "timeAndUserMap": {
          "13:00-14:00": "z"
        }
      }
    ]
  },
  {
    "identifier": "C2",
    "reservationsList": [
      {
        "date": "03/25/24",
        "timeAndUserMap": {
          "13:00-14:00": "m"
        }
      }
    ]
  },
  {
    "identifier": "C6",
    "reservationsList": [
      {
        "date": "03/25/24",
        "timeAndUserMap": {
          "13:00-14:00": "fr"
        }
      }
    ]
  },
  {
    "identifier": "C8",
    "reservationsList": [
      {
        "date": "03/25/24",
        "timeAndUserMap": {
          "13:00-14:00": "p"
        }
      }
    ]
  },
  {
    "identifier": "C9",
    "reservationsList": [
      {
        "date": "03/25/24",
        "timeAndUserMap": {
          "7:00-9:00": "p"
        }
      }
    ]
  }
]